prezident_pr
