Metadata-Version: 2.1
Name: prezident-pr
Version: 1.0.3
Summary: UNKNOWN
Home-page: UNKNOWN
License: UNKNOWN
Platform: UNKNOWN
